setup.py
db/__init__.py
db/db_init.py
testdb.egg-info/PKG-INFO
testdb.egg-info/SOURCES.txt
testdb.egg-info/dependency_links.txt
testdb.egg-info/requires.txt
testdb.egg-info/top_level.txt