Metadata-Version: 1.0
Name: testdb
Version: 1.0.0.2
Summary: db sdk
Home-page: UNKNOWN
Author: skyeye
Author-email: skyeye@gmail.com
License: MIT Licence
Keywords: test,xxx
Platform: any
